fayadateconverter/UmalqurraArray.py
fayadateconverter/__init__.py
fayadateconverter/datetime.py
fayadateconverter/gregorian.py
fayadateconverter/hijri.py
fayadateconverter/jalali.py
fayadateconverter-0.0.1.dist-info/LICENSE
fayadateconverter-0.0.1.dist-info/METADATA
fayadateconverter-0.0.1.dist-info/WHEEL
fayadateconverter-0.0.1.dist-info/top_level.txt
fayadateconverter-0.0.1.dist-info/RECORD
