Metadata-Version: 2.1
Name: fayadateconverter
Version: 0.0.1
Summary: Calendar_gregorian_hijri_jalali
Author: Fatemeh Yahyapour
Classifier: Programming Language :: Python :: 3
Classifier: License :: OSI Approved :: MIT License
Classifier: Operating System :: OS Independent
License-File: LICENSE
